Workbook

Sheet Dashboard
A1: FY2026 PROFIT & LOSS DASHBOARD
A2: Sample Co. | Year-to-date performance at a glance
B4: TOTAL REVENUE (YTD) | E4: NET PROFIT (YTD) | H4: NET PROFIT MARGIN | K4: OPERATING PROFIT (YTD)
B5: ='Monthly P&L'!N10 -> 729500 | E5: ='Monthly P&L'!N40 -> 159343 | H5: ='Monthly P&L'!N41 -> 0.21842769 | K5: ='Monthly P&L'!N30 -> 203800
B6: ="vs. budget: "&TEXT('Budget vs Actual'!E5,"+0.0%;-0.0%") -> vs. budget: +4.2% | E6: ="vs. budget: "&TEXT('Budget vs Actual'!E10,"+0.0%;-0.0%") -> vs. budget: +2.8% | H6: ="Gross margin: "&TEXT('Monthly P&L'!N18,"0.0%") -> Gross margin: 71.5% | K6: ="Operating margin: "&TEXT('Monthly P&L'!N31,"0.0%") -> Operating margin: 27.9%
A49: All figures are illustrative sample data. See the Notes tab for assumptions. Built as a template — replace the yellow input cells on Monthly P&L and Budget vs Actual with your own numbers.

Sheet Monthly P&L
A1: MONTHLY PROFIT & LOSS STATEMENT
A2: Sample Co. | FY2026 | Figures in USD
A3: Yellow cells are sample monthly inputs — replace with your own actuals. Every total, margin, and YTD figure recalculates automatically.
A5: Line Item | B5: Jan | C5: Feb | D5: Mar | E5: Apr | F5: May | G5: Jun | H5: Jul | I5: Aug | J5: Sep | K5: Oct | L5: Nov | M5: Dec | N5: YTD
A6: REVENUE
A7: Product Sales | B7: 42000 | C7: 43500 | D7: 45000 | E7: 44000 | F7: 46000 | G7: 48000 | H7: 41000 | I7: 40000 | J7: 47000 | K7: 50000 | L7: 52000 | M7: 58000 | N7: =SUM(B7:M7) -> 556500
A8: Service Revenue | B8: 12000 | C8: 12500 | D8: 13000 | E8: 13500 | F8: 14000 | G8: 14500 | H8: 13000 | I8: 12800 | J8: 14200 | K8: 15000 | L8: 15500 | M8: 16500 | N8: =SUM(B8:M8) -> 166500
A9: Other Income | B9: 0 | C9: 0 | D9: 1500 | E9: 0 | F9: 0 | G9: 0 | H9: 0 | I9: 2000 | J9: 0 | K9: 0 | L9: 0 | M9: 3000 | N9: =SUM(B9:M9) -> 6500
A10: TOTAL REVENUE | B10: =B7+B8+B9 -> 54000 | C10: =C7+C8+C9 -> 56000 | D10: =D7+D8+D9 -> 59500 | E10: =E7+E8+E9 -> 57500 | F10: =F7+F8+F9 -> 60000 | G10: =G7+G8+G9 -> 62500 | H10: =H7+H8+H9 -> 54000 | I10: =I7+I8+I9 -> 54800 | ... N10: =N7+N8+N9 -> 729500
A12: COST OF GOODS SOLD
A13: Materials & Supplies | B13: 9000 | C13: 9300 | D13: 9600 | E13: 9400 | F13: 9800 | G13: 10200 | H13: 8700 | I13: 8500 | J13: 10000 | K13: 10600 | L13: 11000 | M13: 12300 | N13: =SUM(B13:M13) -> 118400
A14: Direct Labor | B14: 7000 | C14: 7100 | D14: 7300 | E14: 7200 | F14: 7400 | G14: 7600 | H14: 7000 | I14: 6900 | J14: 7500 | K14: 7800 | L14: 8000 | M14: 8600 | N14: =SUM(B14:M14) -> 89400
A15: TOTAL COST OF GOODS SOLD | B15: =B13+B14 -> 16000 | C15: =C13+C14 -> 16400 | D15: =D13+D14 -> 16900 | E15: =E13+E14 -> 16600 | F15: =F13+F14 -> 17200 | G15: =G13+G14 -> 17800 | H15: =H13+H14 -> 15700 | I15: =I13+I14 -> 15400 | ... N15: =N13+N14 -> 207800
A17: GROSS PROFIT | B17: =B10-B15 -> 38000 | C17: =C10-C15 -> 39600 | D17: =D10-D15 -> 42600 | E17: =E10-E15 -> 40900 | F17: =F10-F15 -> 42800 | G17: =G10-G15 -> 44700 | H17: =H10-H15 -> 38300 | I17: =I10-I15 -> 39400 | ... N17: =N10-N15 -> 521700
A18: Gross Margin % | B18: =IFERROR(B17/B10,"n/a") -> 0.7037037 | C18: =IFERROR(C17/C10,"n/a") -> 0.70714286 | D18: =IFERROR(D17/D10,"n/a") -> 0.71596639 | E18: =IFERROR(E17/E10,"n/a") -> 0.71130435 | F18: =IFERROR(F17/F10,"n/a") -> 0.71333333 | G18: =IFERROR(G17/G10,"n/a") -> 0.7152 | H18: =IFERROR(H17/H10,"n/a") -> 0.70925926 | I18: =IFERROR(I17/I10,"n/a") -> 0.7189781 | ... N18: =IFERROR(N17/N10,"n/a") -> 0.71514736
A20: OPERATING EXPENSES
A21: Salaries & Benefits | B21: 15000 | C21: 15000 | D21: 15000 | E21: 15500 | F21: 15500 | G21: 15500 | H21: 15500 | I21: 15500 | J21: 16000 | K21: 16000 | L21: 16000 | M21: 16000 | N21: =SUM(B21:M21) -> 186500
A22: Marketing & Advertising | B22: 4000 | C22: 4200 | D22: 4500 | E22: 4300 | F22: 4600 | G22: 5000 | H22: 3800 | I22: 3600 | J22: 4800 | K22: 5200 | L22: 5500 | M22: 6500 | N22: =SUM(B22:M22) -> 56000
A23: Rent & Utilities | B23: 3200 | C23: 3200 | D23: 3200 | E23: 3200 | F23: 3200 | G23: 3200 | H23: 3200 | I23: 3200 | J23: 3200 | K23: 3200 | L23: 3200 | M23: 3200 | N23: =SUM(B23:M23) -> 38400
A24: Software & Subscriptions | B24: 1200 | C24: 1200 | D24: 1250 | E24: 1250 | F24: 1250 | G24: 1300 | H24: 1300 | I24: 1300 | J24: 1300 | K24: 1350 | L24: 1350 | M24: 1350 | N24: =SUM(B24:M24) -> 15400
A25: Professional Services | B25: 800 | C25: 0 | D25: 1200 | E25: 0 | F25: 0 | G25: 1500 | H25: 0 | I25: 0 | J25: 900 | K25: 0 | L25: 0 | M25: 1800 | N25: =SUM(B25:M25) -> 6200
A26: Travel & Entertainment | B26: 600 | C26: 500 | D26: 700 | E26: 650 | F26: 800 | G26: 900 | H26: 400 | I26: 350 | J26: 750 | K26: 850 | L26: 900 | M26: 1100 | N26: =SUM(B26:M26) -> 8500
A27: Other G&A | B27: 500 | C27: 500 | D27: 550 | E27: 500 | F27: 550 | G27: 600 | H27: 500 | I27: 450 | J27: 600 | K27: 650 | L27: 700 | M27: 800 | N27: =SUM(B27:M27) -> 6900
A28: TOTAL OPERATING EXPENSES | B28: =B21+B22+B23+B24+B25+B26+B27 -> 25300 | C28: =C21+C22+C23+C24+C25+C26+C27 -> 24600 | D28: =D21+D22+D23+D24+D25+D26+D27 -> 26400 | E28: =E21+E22+E23+E24+E25+E26+E27 -> 25400 | F28: =F21+F22+F23+F24+F25+F26+F27 -> 25900 | G28: =G21+G22+G23+G24+G25+G26+G27 -> 28000 | H28: =H21+H22+H23+H24+H25+H26+H27 -> 24700 | I28: =I21+I22+I23+I24+I25+I26+I27 -> 24400 | ... N28: =N21+N22+N23+N24+N25+N26+N27 -> 317900
A30: OPERATING PROFIT (EBIT) | B30: =B17-B28 -> 12700 | C30: =C17-C28 -> 15000 | D30: =D17-D28 -> 16200 | E30: =E17-E28 -> 15500 | F30: =F17-F28 -> 16900 | G30: =G17-G28 -> 16700 | H30: =H17-H28 -> 13600 | I30: =I17-I28 -> 15000 | ... N30: =N17-N28 -> 203800
A31: Operating Margin % | B31: =IFERROR(B30/B10,"n/a") -> 0.23518519 | C31: =IFERROR(C30/C10,"n/a") -> 0.26785714 | D31: =IFERROR(D30/D10,"n/a") -> 0.27226891 | E31: =IFERROR(E30/E10,"n/a") -> 0.26956522 | F31: =IFERROR(F30/F10,"n/a") -> 0.28166667 | G31: =IFERROR(G30/G10,"n/a") -> 0.2672 | H31: =IFERROR(H30/H10,"n/a") -> 0.25185185 | I31: =IFERROR(I30/I10,"n/a") -> 0.27372263 | ... N31: =IFERROR(N30/N10,"n/a") -> 0.27936943
A33: OTHER INCOME (EXPENSE)
A34: Interest Income | B34: 100 | C34: 100 | D34: 110 | E34: 110 | F34: 120 | G34: 120 | H34: 130 | I34: 130 | J34: 140 | K34: 140 | L34: 150 | M34: 150 | N34: =SUM(B34:M34) -> 1500
A35: Interest Expense | B35: -300 | C35: -300 | D35: -300 | E35: -300 | F35: -300 | G35: -300 | H35: -300 | I35: -300 | J35: -300 | K35: -300 | L35: -300 | M35: -300 | N35: =SUM(B35:M35) -> -3600
A36: TOTAL OTHER INCOME (EXPENSE) | B36: =B34+B35 -> -200 | C36: =C34+C35 -> -200 | D36: =D34+D35 -> -190 | E36: =E34+E35 -> -190 | F36: =F34+F35 -> -180 | G36: =G34+G35 -> -180 | H36: =H34+H35 -> -170 | I36: =I34+I35 -> -170 | ... N36: =N34+N35 -> -2100
A38: PROFIT BEFORE TAX | B38: =B30+B36 -> 12500 | C38: =C30+C36 -> 14800 | D38: =D30+D36 -> 16010 | E38: =E30+E36 -> 15310 | F38: =F30+F36 -> 16720 | G38: =G30+G36 -> 16520 | H38: =H30+H36 -> 13430 | I38: =I30+I36 -> 14830 | ... N38: =N30+N36 -> 201700
A39: Income Tax Expense | B39: =-MAX(B38,0)*Notes!$B$5 -> -2625 | C39: =-MAX(C38,0)*Notes!$B$5 -> -3108 | D39: =-MAX(D38,0)*Notes!$B$5 -> -3362.1 | E39: =-MAX(E38,0)*Notes!$B$5 -> -3215.1 | F39: =-MAX(F38,0)*Notes!$B$5 -> -3511.2 | G39: =-MAX(G38,0)*Notes!$B$5 -> -3469.2 | H39: =-MAX(H38,0)*Notes!$B$5 -> -2820.3 | I39: =-MAX(I38,0)*Notes!$B$5 -> -3114.3 | ... M39: =-MAX(M38,0)*Notes!$B$5 -> -5397 | N39: =SUM(B39:M39) -> -42357
A40: NET PROFIT / (LOSS) | B40: =B38+B39 -> 9875 | C40: =C38+C39 -> 11692 | D40: =D38+D39 -> 12647.9 | E40: =E38+E39 -> 12094.9 | F40: =F38+F39 -> 13208.8 | G40: =G38+G39 -> 13050.8 | H40: =H38+H39 -> 10609.7 | I40: =I38+I39 -> 11715.7 | ... N40: =N38+N39 -> 159343
A41: Net Profit Margin % | B41: =IFERROR(B40/B10,"n/a") -> 0.18287037 | C41: =IFERROR(C40/C10,"n/a") -> 0.20878571 | D41: =IFERROR(D40/D10,"n/a") -> 0.21256975 | E41: =IFERROR(E40/E10,"n/a") -> 0.21034609 | F41: =IFERROR(F40/F10,"n/a") -> 0.22014667 | G41: =IFERROR(G40/G10,"n/a") -> 0.2088128 | H41: =IFERROR(H40/H10,"n/a") -> 0.19647593 | I41: =IFERROR(I40/I10,"n/a") -> 0.21379015 | ... N41: =IFERROR(N40/N10,"n/a") -> 0.21842769
A43: Note: all figures are illustrative sample data for demonstration purposes only.

Sheet Budget vs Actual
A1: BUDGET vs. ACTUAL — FY2026
A2: Sample Co. | Annual budget targets vs. year-to-date actuals pulled live from the Monthly P&L tab
A4: Line Item | B4: Budget ($) | C4: Actual ($) | D4: Variance ($) | E4: Variance (%) | F4: Performance
A5: Total Revenue | B5: 700000 | C5: ='Monthly P&L'!N10 -> 729500 | D5: =C5-B5 -> 29500 | E5: =IFERROR(D5/B5,"n/a") -> 0.042142857 | F5: =IF(D5>=0,"On Track","Below Budget") -> On Track
A6: Total Cost of Goods Sold | B6: 195000 | C6: ='Monthly P&L'!N15 -> 207800 | D6: =C6-B6 -> 12800 | E6: =IFERROR(D6/B6,"n/a") -> 0.065641026 | F6: =IF(D6<=0,"On Track","Over Budget") -> Over Budget
A7: Gross Profit | B7: =B5-B6 -> 505000 | C7: ='Monthly P&L'!N17 -> 521700 | D7: =C7-B7 -> 16700 | E7: =IFERROR(D7/B7,"n/a") -> 0.033069307 | F7: =IF(D7>=0,"On Track","Below Budget") -> On Track
A8: Total Operating Expenses | B8: 300000 | C8: ='Monthly P&L'!N28 -> 317900 | D8: =C8-B8 -> 17900 | E8: =IFERROR(D8/B8,"n/a") -> 0.059666667 | F8: =IF(D8<=0,"On Track","Over Budget") -> Over Budget
A9: Operating Profit (EBIT) | B9: =B7-B8 -> 205000 | C9: ='Monthly P&L'!N30 -> 203800 | D9: =C9-B9 -> -1200 | E9: =IFERROR(D9/B9,"n/a") -> -0.0058536585 | F9: =IF(D9>=0,"On Track","Below Budget") -> Below Budget
A10: Net Profit | B10: 155000 | C10: ='Monthly P&L'!N40 -> 159343 | D10: =C10-B10 -> 4343 | E10: =IFERROR(D10/B10,"n/a") -> 0.028019355 | F10: =IF(D10>=0,"On Track","Below Budget") -> On Track
A12: Note: Budget figures are illustrative annual targets (sample data). Actuals are pulled live from the Monthly P&L tab's YTD column.
A14: Chart Data | B14: Budget | C14: Actual
A15: Revenue | B15: =B5 -> 700000 | C15: =C5 -> 729500
A16: COGS | B16: =B6 -> 195000 | C16: =C6 -> 207800
A17: OpEx | B17: =B8 -> 300000 | C17: =C8 -> 317900
A18: Net Profit | B18: =B10 -> 155000 | C18: =C10 -> 159343

Sheet Notes
A1: ASSUMPTIONS & NOTES
A3: Assumption | B3: Value | C3: Description / Source
A5: Corporate income tax rate | B5: 0.21 | C5: Sample rate (US federal statutory corporate rate) applied to Profit Before Tax on the Monthly P&L tab. Replace with your entity's effective rate.
A6: All monthly figures | B6: — | C6: Illustrative sample data for demonstration purposes only — not a real company's financials.
A7: Annual budget figures | B7: — | C7: Illustrative management targets (Budget vs Actual tab), set independently of the monthly actuals for comparison purposes.
